wbplot/__init__.py
wbplot/config.py
wbplot/constants.py
wbplot/wbplot.py
wbplot/data/.DS_Store
wbplot/data/Human.scene
wbplot/data/ImageDense.dscalar.nii
wbplot/data/ImageParcellated.dlabel.nii
wbplot/data/README
wbplot/data/scene.zip
wbplot/data/HumanCorticalParcellations/Q1-Q6_RelatedValidation210.CorticalAreas_dil_Final_Final_Areas_Group_Colors.32k_fs_LR.dlabel.nii
wbplot/data/HumanCorticalParcellations/Q1-Q6_RelatedValidation210.L.CorticalAreas_dil_Final_Final_Areas.32k_fs_LR.dscalar.nii
wbplot/data/HumanCorticalParcellations/Q1-Q6_RelatedValidation210.R.CorticalAreas_dil_Final_Final_Areas.32k_fs_LR.dscalar.nii
wbplot/data/HumanCorticalParcellations/S1200.L.flat.32k_fs_LR.surf.gii
wbplot/data/HumanCorticalParcellations/S1200.L.inflated_MSMAll.32k_fs_LR.surf.gii
wbplot/data/HumanCorticalParcellations/S1200.L.midthickness_MSMAll.32k_fs_LR.surf.gii
wbplot/data/HumanCorticalParcellations/S1200.L.very_inflated_MSMAll.32k_fs_LR.surf.gii
wbplot/data/HumanCorticalParcellations/S1200.R.flat.32k_fs_LR.surf.gii
wbplot/data/HumanCorticalParcellations/S1200.R.inflated_MSMAll.32k_fs_LR.surf.gii
wbplot/data/HumanCorticalParcellations/S1200.R.midthickness_MSMAll.32k_fs_LR.surf.gii
wbplot/data/HumanCorticalParcellations/S1200.R.very_inflated_MSMAll.32k_fs_LR.surf.gii
wbplot/examples/save_dscalar.py
wbplot/examples/save_pscalar.py
wbplot/examples/save_pscalar_with_colorbar.py
wbplot/utils/__init__.py
wbplot/utils/images.py
wbplot/utils/plots.py
wbplot-1.0.14.dist-info/LICENSE
wbplot-1.0.14.dist-info/METADATA
wbplot-1.0.14.dist-info/WHEEL
wbplot-1.0.14.dist-info/top_level.txt
wbplot-1.0.14.dist-info/RECORD
