Metadata-Version: 2.1
Name: wbplot
Version: 1.0.14
Summary: A package for automated plotting of neuroimaging maps using Connectome Workbench.
Home-page: https://github.com/jbburt/wbplot
Author: Joshua Burt
Author-email: joshua.burt@yale.edu
License: UNKNOWN
Platform: UNKNOWN
Classifier: Programming Language :: Python :: 3.7
Classifier: License :: OSI Approved :: GNU General Public License v3 (GPLv3)
Requires-Dist: numpy
Requires-Dist: pillow
Requires-Dist: matplotlib
Requires-Dist: nibabel
